lintwork/__init__.py
lintwork/__version__.py
lintwork/main.py
lintwork/cmd/__init__.py
lintwork/cmd/argument.py
lintwork/cmd/banner.py
lintwork/config/__init__.py
lintwork/config/config.py
lintwork/config/config.yml
lintwork/lint/__init__.py
lintwork/lint/lint.py
lintwork/lint/lint_pb2.py
lintwork/lint/lint_pb2_grpc.py
lintwork/logger/__init__.py
lintwork/logger/logger.py
lintwork/printer/__init__.py
lintwork/printer/printer.py
lintwork/proto/__init__.py
lintwork/proto/proto.py
lintwork/queue/__init__.py
lintwork/queue/queue.py
lintwork/work/__init__.py
lintwork/work/abstract.py
lintwork/work/work.py
lintwork/work/commit/__init__.py
lintwork/work/commit/contentcheck.py
lintwork/work/commit/messagecheck.py
lintwork/work/cpp/__init__.py
lintwork/work/cpp/checkpatch.py
lintwork/work/cpp/cpplint.py
lintwork/work/java/__init__.py
lintwork/work/java/aosplint.py
lintwork/work/java/checkstyle.py
lintwork/work/java/javalint.py
lintwork/work/java/stringscheck.py
lintwork/work/make/__init__.py
lintwork/work/make/checkmake.py
lintwork/work/python/__init__.py
lintwork/work/python/flake8.py
lintwork/work/sast/__init__.py
lintwork/work/sast/rapidscan.py
lintwork/work/sca/__init__.py
lintwork/work/sca/licenseclassifier.py
lintwork/work/sca/scancode.py
lintwork/work/shell/__init__.py
lintwork/work/shell/shellcheck.py
lintwork-1.12.0.dist-info/LICENSE
lintwork-1.12.0.dist-info/METADATA
lintwork-1.12.0.dist-info/WHEEL
lintwork-1.12.0.dist-info/entry_points.txt
lintwork-1.12.0.dist-info/top_level.txt
lintwork-1.12.0.dist-info/RECORD
