Metadata-Version: 2.1
Name: lintwork
Version: 1.12.0
Summary: Lint Work
Home-page: https://github.com/devops-lintflow/lintwork
Download-URL: https://github.com/devops-lintflow/lintwork/archive/v1.12.0.tar.gz
Author: Jia Jia
Author-email: angersax@sina.com
License: Apache-2.0
Keywords: lint,work
Classifier: Development Status :: 3 - Alpha
Classifier: Intended Audience :: Developers
Classifier: Programming Language :: Python :: 3
Classifier: License :: OSI Approved :: Apache Software License
Classifier: Operating System :: OS Independent
License-File: LICENSE
Requires-Dist: black
Requires-Dist: colorama
Requires-Dist: coverage
Requires-Dist: coveralls
Requires-Dist: flake8
Requires-Dist: grpcio
Requires-Dist: grpcio-tools
Requires-Dist: hypothesis
Requires-Dist: mypy
Requires-Dist: openpyxl
Requires-Dist: pre-commit
Requires-Dist: pytest
Requires-Dist: pyyaml
Requires-Dist: setuptools
Requires-Dist: twine
Requires-Dist: wheel
